{
  "metadata": {
    "volume": "19",
    "article_number": "058",
    "title": "法兰克时代[324]",
    "file_name": "volume_19_058_弗・恩格斯。法兰克时代539―599.html",
    "chunk_id": "013",
    "total_chunks": 26,
    "chunk_type": "content"
  },
  "raw_text": "\n跟里普利安语不同，长音i（ij）在发音上变作ei，这在中尼德兰语上似乎还没有这样的情形。但是，这个ei在发音上不是像在高地德意志语里那样ei＝ai，而是实际上像e+i，虽然也不像丹麦人和斯拉夫人的ej发音那样的窄。书写出来不是ij，而是ei的二合元音，发音与此稍有不同。与此相应，代替高地德意志语的au的，是ou，ouw。\n元音交替从语形变化中消失了。在变格上，有单数和复数，在动词变化上，直陈式和虚拟式具有同一的词根元音。相反地，在词的构成上，元音交替则表现为双重形式：（1）一切哥特后期的方言所共有的形式，即a经i而变为e；（2）尼德兰语所特有而在以后才发达起来的形式。中尼德兰语，正如里普利安语一样，依然有hus-Haus［家］，brun-braun［褐色的］，rum-geräumig［广阔］，tun-Zaun［垣篱］；复数则为huse，brune。新尼德兰语则只有中尼德兰语和里普利安语向所未见的语形，例如，huis，bruin，ruim，tuin（ui＝高地德意志语的eu）。相反地，以eu代替短音o（高地德意志语的u），则已经侵入中尼德兰语了。例如，jeughet与joghet同时并存，新尼德兰语有jeugd-Jugend［青年］；doghet-Tugend［道德］，dor-Tür［门］，kor-Wahl［选择］，而同时还有带eu的语形；在新尼德兰语则只有deugd，keur，deur。这同十二世纪起在法兰西北部发展起来的语形--以eu代替重读的拉丁语o--，是完全一致的。凯伦注意到了元音交替的第三种情形：在新尼德兰语里，ei是由ê（ee）的元音交替变成的。所有这三种元音交替形态，都是里普利安语以及其他方言所没有的，是尼德兰语的一种特殊的标志。\nAld，alt，old，olt，uld，ult变为oud，out。这种变化，在中尼德兰语里就已经可以看到了，不过，在那里，既有goudin，houde，scoude（sollte），同时也有guldin，hulde，sculde，因此，这种转变发生于什么时候，是可以大致确定的。这也同样是尼德兰语的特点，至少它同所有大陆的日耳曼方言是相反的；它在英格兰的郎卡郡方言里反而还存在着；例如，gold，hold，old，在那里是gowd，howd，owd。\n说到辅音，尼德兰语没有纯粹的g（即意大利语、法语或英语的后舌音g）。这个辅音的发音像强烈的送气音gh，在若干音结合中，它和深后舌音（瑞士语、现代希腊语或俄语的）ch是没有分别的。我们已经看到，从g到ch的这种转变，在古代萨利克语中就已经出现了。它也出现在一部分的里普利安语和在以前法兰克土地上形成的萨克森方言里，例如，在闵斯德，也跟在贝尔格语里一样，甚至单词的开头的j，特别是在外来语里，在某些场合发音也和ch一样，人们在那里可以听到Choseph，甚至可以听到Chahr（Jahr）。倘使摩・海奈注意到这一点，那末，在古福音诗中j，g和ch的常常彼此换用和互押头韵，就不致于使他感到困惑了。\n在单词的开头，尼德兰语有时还保留着wr，例如wringen-ringen［扭夺］，wreed-grausam［残忍的］，wreken-rächen［复仇］。在里普利安语里，也有这一方面的残迹。\n从弗里西安语里，采纳了将指小词词尾ken软化为tje，je的办法，例如，mannetje-Männchen［小人儿］，bietje-Bienchen［蜜蜂儿］，halsje-Hälschen［围脖儿］，等等。不过，也有保留k的，例如，vrouken-Frauchen［爱妻］，hoeteken-Hüttchen［小屋］。在佛来米语里，至少在民间语言里，k却保留得更好：布鲁塞尔的著名的小人儿叫做manneken-pis[344]。可见法国人的mannequin，英国人的mannikin，都是从佛来米语那里借来的。两者词尾的复数为vroukens，mannetjes。这个s，我们在里普利安语里还会看到。\n尼德兰语同萨克森诸方言，甚至同斯堪的那维亚诸方言共同的地方，是元音之间的ｄ的脱落，特别是两个e之间的d，例如，leder和leer，weder和weer，neder和neer，vader和vaer，moeder和moer-Mutter［母］。\n尼德兰语的变格显示着强变化和弱变化语形的完全的混合，而因为在复数时无元音交替，所以尼德兰语复数的形成，只有在极少的场合，才是与里普利安语或萨克森语一致的，在这里，也可以看出这种语言的一种极其显著的特点。\n萨利克语和里普利安语同一切印格伏南方言共同的地方，是er，der，wer等主格标志的脱落，即在尼德兰语里是hij，de（冠词）和die（指示代词），wie。\n动词变位的分析，会使我们跑得过远。"
}