{
  "metadata": {
    "volume": "30",
    "article_number": "188",
    "title": "马克思致恩格斯",
    "file_name": "volume_30_188_188．马克思致恩格斯（3月24日）330.html",
    "chunk_id": "002",
    "total_chunks": 3,
    "chunk_type": "content"
  },
  "raw_text": "\n没落帝国（Lower　Empire）――在历史文献上是指拜占庭帝国；现在已泛指处于没落腐朽阶段的国家。――第322、332页。\n[309]布斯特拉巴是路易・波拿巴的绰号，由布伦、斯特拉斯堡、巴黎三城的名称的头几个字合成。这个绰号暗指波拿巴在斯特拉斯堡（1836年10月30日）和在布伦（1840年8月6日）进行波拿巴主义叛乱的尝试以及在1851年12月2日在巴黎举行的政变，这次政变在法国建立了波拿巴独裁政权。――第325、332、341、365、379、387、534页。\n[314]在波兰起义初期，梁格维奇在波兰南部散多梅希省率领起义者的最大的部队，与沙皇军队多次成功地作战。1863年3月11日，梁格维奇在波兹南和加里西亚地主集团以及保守的地主资产阶级“白党”的领导上层的发起和支持下，宣布自己为独裁者。依靠幕后的阴谋而确立的这种专政，同小贵族小资产阶级“红党”的中央民族委员会（起临时国民政府的作用）所体现的对起义实行的革命领导相对抗。然而3月19日，梁格维奇在沙皇军队优势兵力的逼迫下抛弃自己的部队，逃往奥地利；他在那里被扣留；他的部队瓦解了。――第331页。\n[315]马克思所引的是普鲁士内务大臣罗霍夫1838年1月15日给埃尔宾城居民的信中的话，该城居民对七个怀有反对派情绪的教授被赶出汉诺威议会一事表示不满。罗霍夫写道：“忠良的臣民要对自己的国王和君主表现出应有的服从，但是不应当在自己的有限理智的范围内试图干预国君的事务。”――第331页。\n[316]看来，是指西华德呈交华盛顿国会的外交公文。关于这件事，详见马克思《华盛顿政府与西方列强》一文（《马克思恩格斯全集》中文版第15卷第451―453页）。――第331页。\n[317]暗指帕麦斯顿政府对1830―1831年的波兰起义所采取的叛卖政策。英国官方集团在1863年也采取了类似的立场，当时他们一方面表示同情波兰人民，―方面却声明不给波兰起义以任何援助。――第332页。\n[318]指的是1863年3月底郎卡郡工业城市埃士顿和斯泰里布雷芝失业纺织工人因饥饿而发生的暴动，暴动与英国在1861―1865年美国内战期间发生棉业危机（见注221）有关。为了镇压失业者当时投入了大批警察以及正规的骑兵和步兵。――第333页。"
}