{
  "metadata": {
    "volume": "44",
    "article_number": "010",
    "title": "*对蒲鲁东的《十九世纪革命的总观念》一书的批判分析[142]",
    "file_name": "volume_44_010_弗・恩格斯。_对蒲鲁东的《十九世纪革命的总观念》一书的批判分析164―196.html",
    "chunk_id": "003",
    "total_chunks": 14,
    "chunk_type": "content"
  },
  "raw_text": "\n酒类、肉类等的消费量减少；“招兵时对身高的要求”降低和不适于服兵役的人数增加：1830―1839年――[45+（1/2）]％，1839―1848年――[50+（1/2）]％；普遍教育不适应现代社会状况；犯罪行为增加：\n1827年――34908件刑事案件，被告47443人\n1846年――80891件刑事案件，被告101433人\n1847年――95914件刑事案件，被告124159人\n违警法庭审理的：\n1829年――108390件，被告159740人\n1845年――152923件，被告197913人\n1847年――184922件，被告239291人\n3．《政府的反常，暴政和营私舞弊的趋势》\n1848年以前，工人甚至普遍得到政府方面的慈善性照顾，从1848年以后进了一步：人们开始明白，只有革命才能在这里作出某种激进的事情，然而情况也只是如此。\n1814年国债的利息为6300万，而现在为27100万。1802年的预算是58900万，1848年是169200万；它的增长不能用政府的愚蠢和居心不良来解释。从1830年到1848年，支付给官吏的薪俸总额增加了6500万。原因同样。\n（法国共有官吏568365人，蒲鲁东根据这个数字计算出，每九人中有一人靠预算生活，也就是说，法国总共只有男子5115285人，而1848年\n**\n投票的人\n**\n竟超过650万！）（第62页）。\n官吏数量的这种增加和军事预算的增长证明加强惩治权力的必要性在增长，从而证明无产阶级\n［注：蒲鲁东著作中是：“des　classes　laborieuses”（“劳动者阶级”）（第63页）。――编者注］\n对国家的危险在增长。国家支持大地产和资本的这种趋势直接导致营私舞弊，而营私舞弊则是一切集中化的直接后果。\n――结果是：\n“十九世纪革命有充分的理由”。\n此外，在这第二篇里还遇到如下的妙论：\n（1）“现行的税收制度……打算让生产者支付一切，而资本家分文不出。\n__\n**\n实际上十分明显的是\n**\n__\n，即使后者作为某一款项的缴纳者列入税务官员的账簿或者他缴纳国库规定的消费品税款，他那只是从他的资本里预先得来的、而不是由他的产品的交换得到的收入，也是免税的，\n**\n因为\n__\n交税的只有生产者\n__\n**\n”（第65页）。\n后面的这个“因为”一词包含着第一句话中应当加以证明的那个论点，因而这个论点自然地得到了证明。这就是蒲鲁东先生的坚定的逻辑。他又对这个论点作了进一步的阐述：\n“\n__\n**\n这样\n**\n__\n，资本和当局之间存在着只让劳动者负担税款的协议，我已经说过，这种协议的秘密只是\n__\n**\n征收产品税而不规定资本税\n**\n__\n。资本所有者借助这种掩人耳目的手法制造一种\n__\n**\n假象，似乎他同其他一切公民一样地\n**\n__\n为自己的土地、自己的房屋、自己的动产、自己的财产转让的交易、自己的旅行和自己的消费\n__\n**\n纳税\n**\n__\n。因此，他硬说，假如他的收入在纳税之前是3000、6000、10000或20000法郎，由于纳税，就不会超过2500、4500、8000或15000法郎。在这种情况下，他对预算的膨胀比他的房客更为不满。纯粹是欺骗！\n__\n**\n资本家分文不出：政府同他处于同等地位，就是这么一回事\n**\n__\n。”\n（当政府从生产者那里拿走一部分产品时，它也同生产者处于同等地位，甚至可以说，资本家也同生产者处于同等地位。）\n“政府和资本家在作共同的事情”\n（啊，施蒂纳！）。\n“\n__\n**\n若能作为2000法郎利息的收入者而列入纳税人账簿，其唯一的条件是用利息的四分之一去偿付税款，有哪个劳动者不认为这是福气呢？\n**\n__\n”！！！（第65―66页）\n（2）土地册是这样编制的，“似乎立法者\n［注：蒲鲁东著作中是：“1789年的立法者”（第66页）。――编者注］\n的目的是恢复不动产的不可转让性，似乎这个立法者竭力不断地使8月4日夜里获得解放的农民[151]回想起他以往的奴隶地位，回想起占有土地的权利并不属于他，以及每个庄户人如果没有从君主那里得到赠与证书，他就完全有理由被认为是长期佃户和没有权利支配自己财产的农奴[emphytéote　et　mainmortable]！”（第66页）。\n啊，施蒂纳！似乎大地产和小地产有同样的理由不应当记入土地册，这样一来，路易－菲力浦本人也是农奴了。\n（3）自由贸易的构思和对保护关税的说明。\n关税给国家提供16000万。假定关税被取消，外国竞争在法国市场上加剧。“假定那时政府向法国工业家提出如下的问题：要么支付给我16000万，要么还是把这笔钱留在自己手上，你们为了保护自己的利益宁愿要哪一条？你们是不是认为工业家会选择第一条建议呢？政府强加给他们的正是这一条。"
}