{
  "metadata": {
    "volume": "36",
    "article_number": "302",
    "title": "致弗洛伦斯・凯利-威士涅威茨基夫人",
    "file_name": "volume_36_302_302．致弗洛伦斯・凯利－威士涅威茨基夫人（12月28日）574.html",
    "chunk_id": "002",
    "total_chunks": 3,
    "chunk_type": "content"
  },
  "raw_text": "但是，“骑士团”的领导实际上反对工人参加政治斗争，并主张阶级合作。1886年，“骑士团”的领导反对全国性罢工，禁止它的成员参加罢工，尽管如此，“骑士团”的普通成员还是参加了罢工。此后，“骑士团”失去了它在工人群众中的影响，到九十年代末就瓦解了。――第499、522、558、564、566、576、635页。\n[541]凯利-威士涅威茨基夫人在1886年12月10日的信中，请求恩格斯为她翻译的《1844年英国工人阶级状况》一书的美国版写一篇序言。她为此提出的理由是，恩格斯在1886年2月为他这本书的美国版所写的跋已经过时，所以请他写篇新的序言，着重批判一下亨・乔治的学说。在这封信里，凯利-威士涅威茨基夫人还问恩格斯，他是否同意在该书书名中把“1844年”这几个字删掉。――第574页。\n[542]恩格斯指的是《共产党宣言》中下面这段话：“共产党人为工人阶级的最近的目的和利益而斗争，但是他们在当前的运动中同时代表运动的未来。”（见《马克思恩格斯全集》中文版第4卷第502页）――第576页。"
}