{
  "metadata": {
    "volume": "38",
    "article_number": "039",
    "title": "致卡尔・考茨基",
    "file_name": "volume_38_039_39．致卡尔・考茨基（4月7日）70.html",
    "chunk_id": "002",
    "total_chunks": 3,
    "chunk_type": "content"
  },
  "raw_text": "\n[34]指德国工人运动中两派的合并，即以奥・倍倍尔和威・李卜克内西为首的社会民主工党（爱森纳赫派）和以哈赛尔曼、哈森克莱维尔等人为首的拉萨尔派的全德工人联合会的合并。两派的合并是在1875年5月22―27日哥达合并代表大会上实现的。合并后的党命名为德国社会主义工人党。德国工人阶级队伍中的分裂状态从而宣告结束。但是，向哥达代表大会提出的合并后的党的纲领草案（草案的主要起草人是威・李卜克内西，他在这个问题上采取了调和的立场），包含了严重的错误和对拉萨尔派的原则让步。马克思在《哥达纲领批判》和1875年5月5日给威・白拉克的信中，恩格斯在1875年3月18―28日给奥・倍倍尔的信中，表示赞同建立德国统一的社会主义党，同时警告爱森纳赫派的领导人不要急于求成，不要同拉萨尔派在思想上进行妥协。他们也批判了纲领草案的错误论点，可是，该纲领草案只是略加修改，便在代表大会上通过了。――第20、68、71、74、82、84、87页。\n[77]第二次国际社会主义工人代表大会于1891年8月16―22日在布鲁塞尔举行。出席代表大会的有来自欧洲许多国家和美国的三百三十七名代表。就其组成来看，这基本上是一次马克思派的代表大会。可能派（见注30）的首领们要把大会的召开控制在自己手里的企图遭到了失败，因而没有出席。大会以多数票通过了一项决定，不许来到代表大会的无政府主义者参加代表大会的工作。英国工联的代表出席了代表大会，恩格斯认为这是一件极好的事情。美国代表中间，除了社会主义者外，还有美国工会组织的代表。\n代表大会的议程有关于劳工保护法、关于罢工和抵制、关于军国主义、关于庆祝五一节等问题。\n关于第一个问题的决议中，号召全世界工人把自己的力量联合起来，反对资本家的统治，在工人有政治权利的地方，应当利用这些权利，使自己摆脱雇佣奴隶的地位。在关于罢工和抵制的决议中，代表大会建议工人采用这些斗争手段。这一决议特别强调了工会组织对工人的绝对必要性。\n代表大会的中心问题是关于工人阶级对军国主义的态度问题。在李卜克内西和瓦扬就这个问题所做的报告以及李卜克内西提出的决议案中，包含了这样一些论点：军国主义是资本主义制度的必然产物，只有建立社会主义社会才能彻底铲除军国主义和导致各国人民之间的和平，真正主张和平的政党是社会主义者的党。但是，决议案中没有明确规定反对战争威胁的具体任务和斗争手段。\n荷兰代表、第二国际中半无政府主义者的头子多・纽文胡斯反对李卜克内西的决议案。他提出了另一个决议案，根据这个决议案，每当发生战争的时候，各国社会主义者都应当号召本国人民起来举行总罢工。纽文胡斯的无政府主义空谈没有得到代表大会的支持。绝大多数代表投票赞成威・李卜克内西提出的决议案。\n布鲁塞尔代表大会的决议对国际工人运动具有重大意义。恩格斯把代表大会的结果看作“马克思主义者在原则上和策略上的胜利”。――第62、68、71、77、121、124、132―135、137、141、144―146、149、163、204页。\n[87]指康・施米特拒绝请他到《新时代》编辑部工作的建议一事；1891年4月5日，考茨基将此事写信告诉恩格斯。――第70页。\n[88]恩格斯指的是卡・考茨基的《布伦坦诺是怎样诋毁马克思的》（《Wie　Brentano　Marx　vernichtet》）一文，载于1890―1891年《新时代》第2卷第32期。这是对《资本论》第一卷德文第四版和恩格斯的《布伦坦诺contra马克思》一文的评论。――第70页。"
}