{
  "metadata": {
    "volume": "29",
    "article_number": "164",
    "title": "恩格斯致马克思",
    "file_name": "volume_29_164_164．恩格斯致马克思（10月21日）349.html",
    "chunk_id": 0,
    "total_chunks": 2,
    "chunk_type": "notes"
  },
  "raw_text": "编辑注释: ［注：奥古斯特・维利希。――编者注］\n\n编辑注释: ［注：威廉亲王。――编者注］\n\n编辑注释: ［注：弗・恩格斯《俄国在远东的成功》。――编者注］\n\n编辑注释: ［注：弗・恩格斯指自己迁居新住所。――编者注］\n\n编辑注释: ［注：卡・马克思《政治经济学批判》。――编者注］\n\n编辑注释: ［注：马克思的母亲罕丽达・马克思。――编者注］\n\n编辑注释: **注释：**[284]《我们的时代。百科辞典年鉴》1858年莱比锡布罗克豪斯出版公司版第2卷（《Unsere　Zeit．Jahrbuch　zum　Conversations-Lexikon》．Zweiter　Band．Leipzig，F．A．Brockhaus．1858）。――第350页。"
}