{
  "metadata": {
    "volume": "27",
    "article_number": "047",
    "title": "马克思致恩格斯",
    "file_name": "volume_27_047_马克思致恩格斯（1850年12月2日）.html",
    "chunk_id": "004",
    "total_chunks": 5,
    "chunk_type": "content"
  },
  "raw_text": "为了划清伦敦流亡者中无产阶级分子和小资产阶级分子的界限，该委员会根据马克思和共产主义者同盟其他领导人的提议，于1849年12月3日被改组为社会民主主义流亡者委员会，马克思和恩格斯都参加了它的领导。这个委员会在恢复共产主义者同盟盟员之间的联系方面，在团结在伦敦的马克思和恩格斯的拥护者方面，以及在1849—1850年改组共产主义者同盟方面都起了重要的作用。在共产主义者同盟分裂以后，因流亡者委员会大多数委员落在维利希—沙佩尔集团的影响之下，1850年9月中，马克思和恩格斯以及拥护他们的人宣布退出这个组织（见《马克思恩格斯全集》中文版第7卷第484页）。——第169、343、347、547、551、558页。\n[162]马克思是指欧洲民主派中央委员会的宣言《告德国人》，这个宣言刊登在1850年11月17日该委员会的刊物《流亡者之声》（《La　Voix　du　Proscrit》）上面。\n欧洲民主派中央委员会是根据马志尼的倡议于1850年6月在伦敦成立的。加入该委员会的还有赖德律－洛兰、达拉什和卢格。该委员会是联合各国资产阶级和小资产阶级流亡者的组织。这个无论在其成分上和思想立场上都极端复杂的组织存在时间不长，由于意大利和法国民主派流亡者之间的关系尖锐化，欧洲民主派中央委员会于1852年3月实际上已经瓦解。——第169、341、570、583、594页。\n[163]指共产主义者同盟分裂后于1850年10月成立的科伦共产主义者同盟中央委员会的委员们。——第170、356页。"
}