{
  "metadata": {
    "volume": "42",
    "article_number": "027",
    "title": "对共产主义者的迫害和驱逐",
    "file_name": "volume_42_027_弗・恩格斯。对共产主义者的迫害和驱逐298―299.html",
    "chunk_id": 0,
    "total_chunks": 2,
    "chunk_type": "notes"
  },
  "raw_text": "编辑注释: ［注：《莱茵社会改革年鉴》。――编者注］\n\n编辑注释: ［注：见本卷第294―297页。――编者注］\n\n编辑注释: **注释：**[155]“青年德意志”――三十年代初在瑞士建立（1834年成立）的德国流亡者的秘密革命协会；它同“青年欧洲”（见注106）这个组织有联系。最初在“青年德意志”中起重要作用的是德国小资产阶级流亡者（大学生、政论家及其他人），他们的目的是通过密谋的途径在德国建立共和制度。不久，它的活动日益受到主张公开宣传共产主义思想的工人联合会和共产主义俱乐部的会员的影响。在三十年代中，由于德国流亡者被大批驱逐出瑞士，“青年德意志”的活动就停止了。它在瑞士的民主州（日内瓦、窝州）有几个继续进行活动的小组，它们在四十年代又把“青年德意志”恢复起来。“青年德意志”在不主张采取密谋策略的共产主义俱乐部成员的影响下，开始日益注意社会问题。――第294、298页。[158]魏特林及其拥护者于1843年6月被苏黎世当局逮捕，同年9月出庭受审。检察机关无法证实被告犯有叛国和谋反的罪行，遂以教唆反对所有制和亵渎宗教的罪名将魏特林判处徒刑，驱逐出瑞士；并将他的追随者驱逐出苏黎世州。恩格斯在《大陆上社会改革运动的进展》（见《马克思恩格斯全集》中文版第1卷第575―593页）一文中叙述了魏特林的案件。――第298页。"
}